odoo9_addon_auth_from_http_remote_user-9.0.1.0.0.99.dev17-py3.8-nspkg.pth
odoo_addons/auth_from_http_remote_user/README.rst
odoo_addons/auth_from_http_remote_user/__init__.py
odoo_addons/auth_from_http_remote_user/__openerp__.py
odoo_addons/auth_from_http_remote_user/utils.py
odoo_addons/auth_from_http_remote_user/controllers/__init__.py
odoo_addons/auth_from_http_remote_user/controllers/main.py
odoo_addons/auth_from_http_remote_user/i18n/am.po
odoo_addons/auth_from_http_remote_user/i18n/ar.po
odoo_addons/auth_from_http_remote_user/i18n/auth_from_http_remote_user.pot
odoo_addons/auth_from_http_remote_user/i18n/bg.po
odoo_addons/auth_from_http_remote_user/i18n/bs.po
odoo_addons/auth_from_http_remote_user/i18n/ca.po
odoo_addons/auth_from_http_remote_user/i18n/ca_ES.po
odoo_addons/auth_from_http_remote_user/i18n/cs.po
odoo_addons/auth_from_http_remote_user/i18n/da.po
odoo_addons/auth_from_http_remote_user/i18n/de.po
odoo_addons/auth_from_http_remote_user/i18n/el_GR.po
odoo_addons/auth_from_http_remote_user/i18n/en_GB.po
odoo_addons/auth_from_http_remote_user/i18n/es.po
odoo_addons/auth_from_http_remote_user/i18n/es_AR.po
odoo_addons/auth_from_http_remote_user/i18n/es_CL.po
odoo_addons/auth_from_http_remote_user/i18n/es_CO.po
odoo_addons/auth_from_http_remote_user/i18n/es_CR.po
odoo_addons/auth_from_http_remote_user/i18n/es_DO.po
odoo_addons/auth_from_http_remote_user/i18n/es_EC.po
odoo_addons/auth_from_http_remote_user/i18n/es_ES.po
odoo_addons/auth_from_http_remote_user/i18n/es_MX.po
odoo_addons/auth_from_http_remote_user/i18n/es_PE.po
odoo_addons/auth_from_http_remote_user/i18n/es_PY.po
odoo_addons/auth_from_http_remote_user/i18n/es_VE.po
odoo_addons/auth_from_http_remote_user/i18n/et.po
odoo_addons/auth_from_http_remote_user/i18n/eu.po
odoo_addons/auth_from_http_remote_user/i18n/fa.po
odoo_addons/auth_from_http_remote_user/i18n/fi.po
odoo_addons/auth_from_http_remote_user/i18n/fr.po
odoo_addons/auth_from_http_remote_user/i18n/fr_CA.po
odoo9_addon_auth_from_http_remote_user-9.0.1.0.0.99.dev17.dist-info/METADATA
odoo9_addon_auth_from_http_remote_user-9.0.1.0.0.99.dev17.dist-info/WHEEL
odoo9_addon_auth_from_http_remote_user-9.0.1.0.0.99.dev17.dist-info/namespace_packages.txt
odoo9_addon_auth_from_http_remote_user-9.0.1.0.0.99.dev17.dist-info/top_level.txt
odoo9_addon_auth_from_http_remote_user-9.0.1.0.0.99.dev17.dist-info/RECORD
